poselib/__init__.py
poselib/_core.cpython-310-darwin.so
poselib/_core.pyi
poselib/utils.py
poselib-2.0.5.dist-info/licenses/LICENSE
poselib-2.0.5.dist-info/METADATA
poselib-2.0.5.dist-info/WHEEL
poselib-2.0.5.dist-info/top_level.txt
poselib-2.0.5.dist-info/RECORD
