Metadata-Version: 2.1
Name: poselib
Version: 2.0.5
Summary: RANSAC + collection of minimal solvers for camera pose estimation.
Author: Viktor Larsson and contributors
Author-email: Viktor Larsson and contributors <viktor.larsson@math.lth.se>
License: BSD 3-Clause License
Requires-Python: >=3.8
License-File: LICENSE
Requires-Dist: numpy
Provides-Extra: test
Requires-Dist: pytest>=8.3.5; extra == "test"
